README.md
setup.cfg
setup.py
socket_messenger/__init__.py
socket_messenger/socket_messenger.py
socket_messenger.egg-info/PKG-INFO
socket_messenger.egg-info/SOURCES.txt
socket_messenger.egg-info/dependency_links.txt
socket_messenger.egg-info/requires.txt
socket_messenger.egg-info/top_level.txt