Metadata-Version: 1.2
Name: socket-messenger
Version: 0.2a0
Summary: Makes communication between devices using pubnub through Python easy
Home-page: https://github.com/vink246/socket_messenger.git
Author: Vineet Kulkarni
Author-email: 2vineetk@gmail.com
License: UNKNOWN
Download-URL: https://github.com/vink246/socket_messenger/archive/0.2-alpha.tar.gz
Platform: UNKNOWN
Classifier: Programming Language :: Python :: 3
Requires-Python: >=3.5
